fastapi_kickstart/__init__.py
fastapi_kickstart/main.py
fastapi_kickstart-0.1.0.dist-info/LICENSE
fastapi_kickstart-0.1.0.dist-info/METADATA
fastapi_kickstart-0.1.0.dist-info/WHEEL
fastapi_kickstart-0.1.0.dist-info/entry_points.txt
fastapi_kickstart-0.1.0.dist-info/top_level.txt
fastapi_kickstart-0.1.0.dist-info/RECORD
