Metadata-Version: 2.2
Name: fastapi-kickstart
Version: 0.1.0
License-File: LICENSE
Requires-Dist: fastapi
Requires-Dist: uvicorn
Dynamic: description
Dynamic: description-content-type
Dynamic: requires-dist
